<?xml version="1.0" encoding="UTF-8"?>
<help>

<entry id="keyboard-navigation" state="uptodate" md5="885a83e5ce7c455f8d7d40a17ca901df">
    <title>Näppäimistö: Navigointi</title>
    <para>Voit käyttää näppäimistöä liikkumiseen eri näkymissä; Postilaatikkonäkymässä voit nuolinäppäimillä siirtyä sivulta toiselle ja viestiä lukiessa voi siirtyä viestistä toiseen.</para>
    <heading>Viestilista: Näppäimistönavigointi</heading>
    <para>Voit käyttää näppäimistöä viestien valitsemiseen ja liikkumiseen viestilistassa. Viestilistalla voi liikkua pitämällä pohjassa Control (CTRL)-näppäintä ja kursorinäppäimien ylös- ja alas-näppäimillä. Jos painat ensimmäisenä painalluksena ylös-näppäintä, niin selaaminen alkaa listan alalaidasta (Listan viimeinen viesti). Jos painat ensimmäisenä alas-näppäintä, niin selaaminen alkaa listan ylälaidasta (Listan ensimmäinen viesti).</para>
    <para>Valittu viesti näkyy korostettua eri värisenä samalla tavalla kuin olisit valinnut viestin hiirellä. Voit välilyöntinäppäimellä valita viestin tai poistaa viestin valinnan ja Return-näppäimellä voit aukaista viestin.</para>
    <heading>Viestilista: Edellinen/Seuraava sivu</heading>
    <para>Kursorinäppäimien oikea/vasen-näppäimillä voit siirtyä viestilistanäkymässä sivulta toiselle: oikealla seuraavalle ja vasemmalla edelliselle sivulle.</para>
    <heading>Viestinäkymä: Edellinen/Seuraava viesti</heading>
    <para>Kursorinäppäimien oikea/vasen-näppäimillä voit siirtyä viestiä toiseen: oikealla seuraavaan ja vasemmalle edelliseen viestiin.</para>
</entry>

<!--
<entry id="keyboard-shortcuts">
    <title>Keyboard: Shortcuts</title>
    <heading>Using Keyboard Shortcuts</heading>
</entry>
-->

<entry id="compose-buttons" state="uptodate" md5="bd0e2b0eff15d7c5cf7df9b7ef4ac40a">
    <title>Viestin kirjoitus: Toiminnot</title>
    <heading>Toiminnot</heading>
    <para>
    "Lähetä viesti" lähettää viestin vastaanottajille. Muistathan että
    viestiä ei voi enää perua kun se on lähetetty matkaan.
    </para>
    <para>
    "Tallenna luonnos" tallettaa keskeneräisen viestin kansioon
    "Luonnos". Kansiota voi käsitellä alasvetovalikosta ruudun
    oikeasta yläkulmasta. Voit viimeistellä viestisi siirtymällä
    "Luonnos" kansioon, valitsemalla sieltä viestin ja painamalla
    painiketta "Jatka". Muistathan aina laittaa viesteihin kuvaavan
    otsikon ennenkuin talletat ne luonnoskansioon. Hyvä otsikko
    helpottaa myöhemmin tilannetta kun pitää löytää oikea viesti.
    </para>
    <tip>
    Asennuksesta riippuen voit valita asetuksistasi palaatko viimeksi
    selailemaasi kansioon tai viimeksi lukemaasi viestiin kun viesti
    on talletettu luonnokseksi.
    </tip>
    <para>
    "Peru viesti" hylkää kirjoittamasi viestin ja palauttaa sinut
    siihen kansioon mitä olit viimeksi selaillut.
    </para>
</entry>

<entry id="compose-identity" state="uptodate" md5="6b2272c5440c753e783d000db88fea07">
    <title>Viestin kirjoitus: Profiili</title>
    <heading>Profiili</heading>
    <para>Lähetysprofiili on mahdollista valita alasvetolistasta. Listassa näkyy ne profiilit, jotka olet aikaisemmin määritellyt <qt>Asetukset-&gt;Omat tiedot</qt>.</para>
</entry>

<entry id="compose-from" state="uptodate" md5="4395043c22323cc80d50709c5d20637e">
    <title>Viestin kirjoitus: Lähettäjä</title>
    <heading>Lähettäjä</heading>
    <para>
    Vain jos ylläpitäjä on sallinut tämän toiminnon käyttämisen. Sinun
    on mahdollista valita alasvetovalikosta käytettävä profiili tai
    voit kirjoittaa kenttään lähettäjänä näkyvän
    sähköpostiosoitteen. Profiileja voit määritellä
    <qt>Asetukset-&gt;Omat tiedot</qt>.
    </para>
</entry>

<entry id="compose-to" state="uptodate" md5="31cba17f169572c367aa8014831eb8f8">
    <title>Viestin kirjoitus: Vastaanottaja</title>
    <heading>Vastaanottaja</heading>
    <para>
    Kirjoita tähän viestin vastaanottajan sähköpostiosoite. Jos
    viestillä on useita vastaanottajia, niin erota osoitteet
    toisistaan pilkulla. Minkä tahansa muun merkin käyttäminen
    erottimena aiheuttaa vikatilanteen ja virheilmoituksen.
    </para>
</entry>

<entry id="compose-cc" state="uptodate" md5="97571433ab037ef9c4d101a56bf74e25">
    <title>Viestin kirjoitus: Kopio</title>
    <heading>Kopio</heading>
    <para>
    Kirjoita tähän sähköpostiosoite, johon lähetetään kopio
    viestistä. Jos viestistä lähetetään kopio usealle
    vastaanottajalle, niin erota osoitteet toisistaan pilkulla. Minkä
    tahansa muun merkin käyttäminen erottimena aiheuttaa vikatilanteen
    ja virheilmoituksen.
    </para>
    <para>
    Kopio lähetetään yleensä niille vastaanottajille, jotka eivät ole
    viestin suoranaisia vastaanottajia, mutta voivat tarvita tai olla
    kiinnostuneita viestissä olevista tiedoista. Muistathan että
    vastaanottaja näkee kaikki ne osoitteet, jotka ovat viestin
    vastaanottajina tai joille viestistä on lähetetty kopio.
    </para>
</entry>

<entry id="compose-bcc" state="uptodate" md5="aa8f9e2d44fdb74def0fa15240ff687b">
    <title>Viestin kirjoitus: Piilokopio</title>
    <heading>Piilo</heading>
    <para>
    Kirjoita tähän sähköpostiosoite, johon lähetetään piilokopio
    viestistä. Jos viestistä lähetetään piilokopio usealle
    vastaanottajalle, niin erota osoitteet toisistaan pilkulla. Minkä
    tahansa muun merkin käyttäminen erottimena aiheuttaa vikatilanteen
    ja virheilmoituksen.
    </para>
    <para>
    Piilokopio lähetetään yleensä niille vastaanottajille, jotka eivät
    ole viestin suoranaisia vastaanottajia, mutta voivat tarvita tai
    olla kiinnostuneita viestissä olevista tiedoista. Viestin
    varsinaiset vastaanottajat eivät näe kenelle viesti on mennyt
    piilokopioina. Vain viestin lähettäjä tietää kenelle kaikille
    viesti on lähetetty.
    </para>
</entry>

<entry id="compose-subject" state="uptodate" md5="0639a8790e306acc9e19b4d1ce342d53">
    <title>Viestin kirjotus: Otsikko</title>
    <heading>Otsikko</heading>
    <para>
    Kirjoita tähän viestin otsikko. Viestin otsikko on parasta pitää
    lyhyenä ja yksinkertaisena mutta kuitenkin kuvaavana. Otsikko voi
    auttaa oikean viestin löytämisessä ja myös muistuttaa sinua mistä
    viestissä oli kyse.
    </para>
    <para>
    Muista myös että viestin "Vastaa" tai "Välitä eteenpäin"
    toiminnoissa viestin otsikko kopioidaan uuteen viestiin siten että
    viesteistä näkee mitkä kuuluvat samaan "säikeeseen". Jos viestin
    aihe muuttuu alkuperäisesti otsikosta, niin kannattanee vaihtaa
    myös viestin otsikkoa.
    </para>
</entry>

<entry id="compose-charset" state="uptodate" md5="c2c878070445af81407da5bfc4083ea3">
    <title>Viestin kirjoitus: Merkistö</title>
    <heading>Merkistö</heading>
    <para>Voit listasta valita lähetyksessä käytettävän merkistön.
    </para>
</entry>

<entry id="compose-options" md5="5f1d50a733c8b7e46aecece28822ff70" state="uptodate">
    <title>Viestin kirjoitus: Lisätoiminnot</title>
    <heading>Lisätoiminnot</heading>
    <para>
    Nämä lisätoiminnot ovat apuna viestien kirjoittamiseen.
    </para>
    <para>
    Napsauta "Oikeinkirjoitus" tarkistaaksesi viestin oikeinkirjoituksen.
    </para>
    <para>
    Napsauta "Liitteet" mennäksesi viestisivun loppuun, jossa voit liittää viestiin liitetiedostoja.
    </para>
    <para>
    Vain jos ylläpitäjä on sallinut tämän toiminnon käyttämisen. Voit
    tallettaa viestistä kopion lähtevien viestien kansioon tai
    valitsemaasi kansioon. Lähtevien viestin kansion voi määritellä
    "Asetukset-&gt;Omat tiedot-&gt;Profiilit". Jos ylläpitäjä on
    sallinut toiminnon, niin voit valita talletuskansion
    alasvetovalikosta.
    </para>
    <para>
    Voi olla ihan hyvä tapa tallettaa kopio tärkeäksi katsomistasi
    viesteitä. On myös mahdollista laittaa päälle asetus, jolla
    talletat kopioin kaikista lähtevistä viesteistä
    "Asetukset-&gt;Omat tiedot-&gt;Profiilit-&gt;Muokkaa
    profilia". Asetuksista voit myös määritellä ylläpitotoimenpiteitä,
    joilla voit nimetä nämä kansiot uudestaan tietyin väliajoin.
    </para>
    <warn>
    Sinun ei kannata tallettaa kaikkia viestejä, koska talletetut
    viestit vievät tilaa ja postikiintiötä. Jos sinulla on paljon talletettuja viestejä ja niissä on isoja liitetiedostoja, niin postikiintiösi voi täyttyä hyvinkin nopeasti. Jos postikiintiösi on
    täynnä, niin et voi vastaanottaa uusia viestejä.
    </warn>
</entry>

<entry id="compose-attachments" state="changed" md5="b0d28bb946919a0c13c45721aa5d3f67">
    <title>Viestin kirjoitus: Liitteet</title>
    <heading>Liitteet</heading>
    <para>
    Tässä osiossa on lista liitetyistä liitetiedostoista.
    </para>
    <heading>Poista liitetty liitetiedosto</heading>
    <para>
    Poistaaksesi liitetyn liitetiedoston:
    </para>
    <para>
    Askel 1: Valitse poistettava liitetiedosto käyttäen valintalaatikkoa.
    </para>
    <para>
    Askel 2: Napsauta "Päivitä liitetiedoston tiedot".
    </para>
    <heading>Liitetavan muutos</heading>
    <para>
    Muuttaaksesi liitteen liitetapaa:
    </para>
    <para>
    Askel 1: Muuta liitteen tyyppiä haluttuun muotoon joko "viestin
    yhteydessä" tai "liite".
    </para>
    <para>
    Askel 2: Napsauta "Päivitä liitetiedoston tiedot".
    </para>
    <heading>Muuta liitteen kuvausta</heading>
    <para>
    Muuttaaksesi liitteen kuvausta (kuvaava teksti, joka näkyy viestin vastaanottajalle):
    </para>
    <para>
    Askel 1: Kirjoita kuvaus kuvauskenttään.
    </para>
    <para>
    Askel 2: Napsauta "Päivitä liitetiedoston tiedot". Tiedot päivitetään automaattisesti kun viesti lähetetään.
    </para>
<!-- English entry:
<entry id="compose-attachments">
    <title>Message Composition: Adding Attachments</title>
    <heading>Adding Attachments</heading>
    <para>
    You may attach files to your message if your browser supports uploading of files. More than 1 file can be uploaded at once.
    </para>
    <para>Step 1: Either type the path and name of a file that you want attached to this message or click the "Browse" button and select the file to be attached. The path and name of that file now appears in the Attachment box. If your browser supports JavaScript, you will see an additional upload input now as well, for uploading other files at the same time.
    </para>
    <para>Step 2: Decide whether you want the file to be viewed as an attachment or inline with the rest of the message. The recipient's mail reading software must be able to handle the inline display of the file type, otherwise this part will be viewed as an attachment instead.
    </para>
    <para>
    Unless you want to change an attachment's description or specify that it should be shown to the recipient inline, you are done. The attachments will be uploaded when you send your message. If you want to change the description or the attachment disposition, however, you can click the "Update" button to upload your attachments immediately and save any other changes you've made to existing attachments.
    </para>

    <tip>
    Please note that for large files and/or slower Internet connections, the process of uploading and attaching your file to the email may take a while. Please be patient and do not click other links or buttons while you are waiting for a file to upload.
    </tip>
</entry>--><!-- English entry:
<entry id="compose-attachments">
    <title>Message Composition: Adding Attachments</title>
    <heading>Adding Attachments</heading>
    <para>
    You may attach files to your message if your browser supports uploading of files. More than 1 file can be uploaded at once.
    </para>
    <para>Step 1: Either type the path and name of a file that you want attached to this message or click the "Browse" button and select the file to be attached. The path and name of that file now appears in the Attachment box. If your browser supports JavaScript, you will see an additional upload input now as well, for uploading other files at the same time.
    </para>
    <para>Step 2: Decide whether you want the file to be viewed as an attachment or inline with the rest of the message. The recipient's mail reading software must be able to handle the inline display of the file type, otherwise this part will be viewed as an attachment instead.
    </para>
    <para>
    Unless you want to change an attachment's description or specify that it should be shown to the recipient inline, you are done. The attachments will be uploaded when you send your message. If you want to change the description or the attachment disposition, however, you can click the "Update" button to upload your attachments immediately and save any other changes you've made to existing attachments.
    </para>

    <tip>
    Please note that for large files and/or slower Internet connections, the process of uploading and attaching your file to the email may take a while. Please be patient and do not click other links or buttons while you are waiting for a file to upload.
    </tip>
</entry>--><!-- English entry (2010-08-16):
<entry id="compose-attachments">
    <title>Message Composition: Adding Attachments</title>
    <heading>Adding Attachments</heading>
    <para>
    You may attach files to your message if your browser supports uploading of files. More than 1 file can be uploaded at once.
    </para>
    <para>Step 1: Either type the path and name of a file that you want attached to this message or click the "Browse" button and select the file to be attached. The path and name of that file now appears in the Attachment box. If your browser supports JavaScript, you will see an additional upload input now as well, for uploading other files at the same time.
    </para>
    <para>Step 2: Decide whether you want the file to be viewed as an attachment or inline with the rest of the message. The recipient's mail reading software must be able to handle the inline display of the file type, otherwise this part will be viewed as an attachment instead.
    </para>
    <para>
    Unless you want to change an attachment's description or specify that it should be shown to the recipient inline, you are done. The attachments will be uploaded when you send your message. If you want to change the description or the attachment disposition, however, you can click the "Update" button to upload your attachments immediately and save any other changes you've made to existing attachments.
    </para>

    <tip>
    Please note that for large files and/or slower Internet connections, the process of uploading and attaching your file to the email may take a while. Please be patient and do not click other links or buttons while you are waiting for a file to upload.
    </tip>
</entry>--></entry>

<entry id="compose-current-attachments" state="new">
    <title>Message Composition: Current Attachments</title>
    <heading>Current Attachments</heading>
    <para>
    This section displays a list of files already attached to your message.
    </para>
    <heading>Delete attached file(s)</heading>
    <para>
    To delete an attached file(s):
    </para>
    <para>
    Step 1: Activate the check-button next to the attached filename(s) you want to delete.
    </para>
    <para>
    Step 2: Either click the "Update" button above the Current Attachments section to immediately view changes or the changes will automatically be performed when the message is sent.
    </para>
    <heading>Change Attachment Disposition</heading>
    <para>
    To change the disposition for your attachments:
    </para>
    <para>
    Step 1: Change each attachment's disposition - either "inline" or "attachment" - to the desired value.
    </para>
    <para>
    Step 2: Either click the "Update" button above the Current Attachments section to immediately view changes or the changes will automatically be performed when the message is sent.
    </para>
    <heading>Change Attachment Description</heading>
    <para>
    To change the description for your attachments (the text the recipient will see that describes the attachment):
    </para>
    <para>
    Step 1: Enter a description into the Description field.
    </para>
    <para>
    Step 2: Either click the "Update" button above the Current Attachments section to immediately view changes or the changes will automatically be performed when the message is sent.
    </para>
</entry>

<entry id="compose-priority" state="uptodate" md5="b023367c36de3ce1567d27ccaa45640c">
    <title>Viestin kirjoitus: Prioriteetti</title>
    <heading>Prioriteetti</heading>
    <para>
    Tämä asettaa lähtevän viestin "X-Priority"
    -otsakkeen. "X-Priority" -otsakkeen käytöstä ei ole varsinaista
    standardia, mutta ainakin Netscape, Mozilla, Opera ja Outlook
    käyttävät tätä kenttää. Jos ohjelma ei tue otsaketta, niin ne vain
    jättävät sen huomiotta.
    </para>
</entry>

<entry id="compose-save-attachments" state="uptodate" md5="db89972c4ebb0b41ab691b6a7744a81d">
    <title>Viestin kirjoitus: Liitteiden talletus</title>
    <para>
    Voit valita talletetaanko liite viestin mukana kun viesti
    talletetaan lähtevien viestien kansioon. Jos valitset "Kyllä",
    niin liiteet talletetaan. Jos valitset "Ei", niin liitetiedosto
    poistetaan viestistä ennenkuin se talletaan lähtevien viestien
    kansioon. Valitsemalla "Ei" säästät levytilaa ja voit tallettaa
    useampia viestejä.
    </para>
</entry>

<entry id="compose-link-attachments" state="uptodate" md5="63b3841c95aed31b5372f0fa770ee382">
    <title>Message Composition: Link Attachments</title>
    <para>
    Determines whether the attachments in your composition are sent as a part of the mail message or whether those attachments are kept on a local server.  If attachments are linked, the recipient(s) of your message will be provided a weblink where they can download the attachment(s).  Linking attachments has the advantage of tremendously reducing the size of outgoing messages.  Linking attachments has the disadvantage that the content of the attachments can not be guaranteed to be available in the future since the attachment data is not located within the e-mail message.
    </para>
</entry>

<entry id="folder-options" md5="08ee3e450a82431727763b9db082ec08" state="uptodate">
    <title>Kansioiden hallinta: Toiminnot</title>
    <heading>Kansiotoiminnot</heading>
    <para>
     Voit valita kansion käyttämällä radiopainikkeita vasemmassa
     sarakkeessa. Kun olet valinnut kansiot, niin valitse kansiolle
     tehtävä toiminto alasvetovalikosta.
    </para>
    <para>
      Riippuen toiminnosta, sinulta voidaan kysyä vielä
      lisätietoja. Ole erittäin varovainen Poista toiminnon
      kanssa. Jos poistat kansion, niin poistat myös kaikki kansiossa
      olevat viestit.
    </para>
    <heading>Tuo viestejä</heading>
    <para>
      Tällä toiminnolla voit tuoda viestejä mbox tai .eml tiedostoista
      valitsemaasi kansioon. Valitse ensin yksi kansio, johon viestit
      tuodaan ja valitse sitten tämä toiminto. Sen jälkeen tulet
      sivulle, jossa kysytään tuotko viestejä mbox vai .elm
      tiedostosta.
    </para>
</entry>

<entry id="filters" md5="5ef60786767e638fbf5ba8fc5bd5d9d2" state="uptodate">
    <title>Suodattimet: Käyttö</title>
    <heading>Suodatinsääntöjen käyttö</heading>
    <para>
    Napsauta "Suodata viestit" -ikonia INBOX nimen vieressä
    postikansionäkymässä suodattaaksesi viestit määrittelemiesi
    suodatussääntöjen mukaan.
    </para>
</entry>

<entry id="filter-edit-rules" md5="5baa5708ac9449e797f967313a9e1a27" state="uptodate">
    <title>Suodattimet: Muokkaa suodatinsääntöjä</title>
    <heading>Muokkaa suodatinsääntöjäsi</heading>
    <para>
    Napsauta "Muokkaa suodattimia" päästäksesi sivulle, jossa voit
    lisätä, poistaa ja muokata käytössä olevia suodatinsääntöjä.
    </para>
</entry>

<entry id="filter-edit-blacklist" md5="80ff7803c66599c7035f7f8811d218cc" state="uptodate">
    <title>Suodattimet: Muokkaa mustaa listaa</title>
    <heading>Muokkaa mustaa listaa</heading>
    <para>
    Napsauta "Muokkaa mustaa listaa" päästäksesi sivulla, jossa voit
    lisätä, poistaa ja muokata listaa niistä sähköpostiosoitteista,
    joista et ota vastaan sähköpostia.
    </para>
</entry>

<entry id="filter-edit-whitelist" md5="330c3a8fad198c7afe855c101c63cd0f" state="uptodate">
    <title>Suodattimet: Muokkaa sallittujen listaa</title>
    <heading>Muokkaa sallittujen listaa</heading>
    <para>
    Napsauta "Muokkaa sallittujen listaa" päästäksesi sivulla, jossa
    voit lisätä, poistaa ja muokata listaa niistä
    sähköpostiosoitteista, joista otat AINA vastaan sähköpostia.
    </para>
</entry>

<entry id="filter-on-login" md5="37d9297d1cca46435e36b6e38e45dcdb" state="uptodate">
    <title>Suodattimet: Suodatus sisäänkirjautuessa</title>
    <heading>Suodata viestit sisäänkirjautumisen yhteydessä.</heading>
    <para>
    Kun valitset tämän asetuksen, niin suodattimet ajetaan aina kun
    kirjaudut sisään IMP-ohjelmaan.
    </para>
</entry>

<entry id="filter-on-display" md5="f5afc305402ef52bad108933f3f33291" state="uptodate">
    <title>Suodattimet: Suodata päivityksen yhteydessä</title>
    <heading>Suodata viestit kun INBOX postikansioa päivitetään.</heading>
    <para>
    Kun valitset tämän asetuksen, niin suodattimet ajetaan aina kun
    INBOX:a päivitetään.
    </para>
</entry>

<entry id="filter-any-mailbox" md5="71c51e83909f9d0bd440d220772ee3c6" state="uptodate">
    <title>Suodattimet: Suodata mitä tahansa postikansioa</title>
    <heading>Käytä suodattimia mihin kansioon tahansa.</heading>
    <para>
    Käytä tätä asetusta jos haluat käyttää suodattimia mihin kansioon
    tahansa. Yleensä suodattimia käytetään vain niihin kansioihin,
    joihin tulee uusia viestejä kuten INBOX. Jos tämä asetus on
    valittuna, niin "Suodata viestit" -ikoni tulee kaikkien kansioiden
    kansionäkymiin ja voit käyttää näissäkin kansioissa
    määrittelemiäsi suodattimia. HUOMIO: Suodattimien käyttö muissa
    kuin INBOX kansiossa voi aiheuttaa omituisia lopputuloksia
    (esimerkiksi: suodatin voi aiheuttaa sen että viestejä kopioidaan
    samasta kansiosta samaan kansioon) tai ei-toivottuja lopputuloksia
    (esimerkiksi: viestejä voi siirtyä tai kadota, jos uusia
    suodattimia on tullut käytöön sen jälkeen kun viestit on
    talletettu kansioon).
    </para>
</entry>

<entry id="pgp-compose-attach-pubkey" md5="97446dbbb27616b4fa39be801e10df2d" state="uptodate">
    <title>PGP: Liitä julkinen avain</title>
    <heading>Liitä julkinen avain</heading>
    <para>
    Jos tämä toiminto on valittuna ja jos sinulla on julkinen
    PGP-avain, niin se liitetään lähteviin viesteihin. Voit asettaa
    oletustoiminnon PGP Asetukset näkymästä.
    </para>
</entry>

<entry id="pgp-option-scan-body" md5="6baaada0d46dc1ab0941087f235f359b" state="uptodate">
    <title>PGP: Etsi viestien viestiosasta</title>
    <heading>Etsi viestien viestiosasta</heading>
    <para>
    Jos tämä on valittuna, niin IMP etsii viestin viestiosasta
    PGP-tietoja ja näyttää tulokset jos jotain tietoja
    löytyi. Huomioithan että tämä toiminto voi huomattavasti hidastaa
    koko järjestelmän toimintaa, koska jokainen viesti joudutaan
    käymään kokonaan lävitse.
    </para>
</entry>

<entry id="pgp-option-reply-pubkey" state="new">
    <title>PGP: Validate PGP Public Keys When Replying</title>
    <heading>Validate PGP Public Keys When Replying</heading>
    <para>
    If set, and PGP encryption is used by default for composing messages, IMP will verify that it can access all recipients' public keys when the reply is first created. This has the disadvantage that it may cause a delay in opening the reply window. However, it has the advantage of informing you immediately if you will be able to correctly send the encrypted message to all recipients immediately.
    </para>
</entry>

<entry id="compose-options-encrypt" md5="78ff9bd91687efb91d2798ca0458b5cb" state="uptodate">
    <title>Kirjoitus: Salausasetukset</title>
    <heading>Ei salausta</heading>
    <para>
    Lähetä viesti ilman salausta (selväkielisenä).
    </para>
    <heading>PGP-salattu viesti</heading>
    <para>
    Käyttämällä tätä asetusta voit salata lähtevän viestin käyttäen
    PGP-ohjelmaa ja vastaanottajan julkista avainta. PGP-salatun
    viestin voi lähettää vain ja ainoastaan yhdelle
    vastaanottajalle. Sinulla pitää olla vastaanottajan julkinen avain
    talletettuna osoitekirjaan tai et voi lähettää salattua
    viestiä. Jos viestin lähetys ei onnistu sittenkään ja saat
    virheilmoituksen, niin tarkista että julkisessa avaimessa oleva
    sähköpostiosoite on sama kuin vastaanottajan sähköpostiosoite. Kun
    salaus on onnistunut, niin salattu tieto liitetään lähtevään
    viestiin.
    </para>
    <heading>PGP-allekirjoita viesti</heading>
    <para>
    Käyttämällä tätä asetusta voit sähköisesti allekirjoittaa lähtevän
    viestin käyttäen PGP-ohjelmaa ja vastaanottajan julkista
    avainta. Jos et ole jo antanut salasanatekstiäsi, niin aukeaa
    erillinen ikkuna jossa sinua pyydetään antamaan
    salasanatekstisi. Vastaanottajalla pitää olla talletettuna sinun
    julkinen avaimesi, jotta hän voi tarkistaa viestisi eheyden.
    </para>
    <heading>PGP-salaa ja allekirjoita viesti</heading>
    <para>
    Käyttämällä tätä asetusta voit sähköisesti allekirjoittaa salata lähtevän viestin käyttäen PGP-ohjelmaa. Katso tarkemmat tiedot kohdista "PGP-salattu viesti" ja "PGP-allekirjoita viesti".
    </para>
    <heading>S/MIME-salaa viesti</heading>
    <para>
    Tämän toiminto salaa viestin käyttämällä S/MIME-tekniikkaa, vastaanottajan varmennetta ja sitten lähettää sen. Vastaanottajan varmenne pitää olla tallettettuna osoitekirjaan tai muuten tätä toimintoa ei voi käyttää. Jos varmenne on tallettu osoitekirjaan ja silti käytössä tulee virheitä, niin tarkasta ensin, että vastaanottajan osoite on sama kuin mikä on tallettu osoitekirjaan. Salattu viesti lähetetään liitetiedostona.
    </para>
    <heading>S/MIME-allekirjoita viesti</heading>
    <para>
    Tämän toiminto allekirjoittaa viestin sähköisesti käyttämällä S/MIME-tekniikkaa ja omaa varmennettasi. Jos et ole istunnon aikana antanut varmenteesi salasanatekstiä, niin sitä tullaan kysymään ennen viestin lähetystä.
    </para>
    <heading>S/MIME-salaa ja allekirjoita viesti</heading>
    <para>
    Tämä toiminto ensin sähköisesti allekirjoittaa viestin ja sitten salaa viestin. Katso tarkemmat tiedot kohdista "S/MIME-salaa viesti" ja "S/MIME-allekirjoita viesti".
    </para>
</entry>

<entry id="pgp-overview" md5="24b5138b4b53f73b5f2f2739e4c1858d" state="uptodate">
    <title>PGP: Yleiskuva</title>
    <heading>Mikä on PGP?</heading>
    <para>
    PGP on ohjelma, joka on kehitetty turvaamaan tiedonsiirtoa
    esimerkiksi sähköpostissa ja tiedon turvallista
    talletusta. Ohjelmaa voidaan käyttää salaamaan tietoa ja sillä voi
    tehdä sähköisiä allekirjoituksia. IMP käyttää GnuPG (Gnu Privacy
    Guard) ohjelmaa tähän tarkoitukseen.
    </para>
    <heading>Käytä PGP-toimitoa.</heading>
    <para>
    Jos tämä asetus on valittuna, niin voit luoda tai katsoa
    henkilökohtaisia PGP-avaimia, poistaa tai lisätä osoitekirjaan
    toisten käyttäjien julkisia avaimia, lukea salattua sähköpostia,
    tarkistaa sähköpostin sähköisen allekirjoituksen, lähettää
    salattua sähköpostia tai sähköisesti allekirjoittaa lähtevän
    sähköpostin.
    </para>
</entry>

<entry id="pgp-option-attach-pubkey" md5="561ce43370ac4afbcc3f9818c8fbc2f6" state="uptodate">
    <title>PGP: Asetukset - Liitä julkinen avain</title>
    <heading>Asetukset - Liitä julkinen avain</heading>
    <para>
    Jos tämä asetus on valittuna ja jos sinulla on olemassa julkinen
    PGP-avain, niin se liitetään oletuksena kaikkiin lähteviin
    viesteihin.
    </para>
</entry>

<entry id="pgp-manage-pubkey" md5="b289ea5824b7f69f35c0751497f4e1c3" state="uptodate">
    <title>PGP: Julkisen avaimen hallinta</title>
    <heading>Yleiskuva</heading>
    <para>
    Listaa osoitekirjastasi kaikki ne käyttäjät, joiden julkinen
    PGP-avain on talletettuna osoitekirjaasi. Nämä käyttäjät
    muodostavat joukon, jolle voit lähettää salattua sähköpostia tai
    tarkistaa heidän lähettämänsä sähköisesti allekirjoitetun
    sähköpostin allekirjoituksen.
    </para>
    <heading>Näytä</heading>
    <para>
    Näyttää julkisen PGP-avaimen erillisessä ikkunassa.
    </para>
    <heading>Tarkemmat tiedot</heading>
    <para>
    Näyttää tarkempia tietoja julkisesta PGP-avaimesta.
    </para>
    <heading>Poista</heading>
    <para>
    Poistaa julkisen avaimen osoitekirjastasi.
    </para>
</entry>

<entry id="pgp-import-pubkey" md5="6ee1130b46e9ff1ca9ad3a3a47e7b382" state="uptodate">
    <title>PGP: Julkisen avaimen hallinta - Tuonti</title>
    <heading>Tuo julkisia avaimia</heading>
    <para>
    Tästä  painikkeesta  aukeaa   ikkuna,  johon  voi  tuoda  julkisen
    PGP-avaimen. Voit  kopioida ja liittää  avaimen tekstikenttään tai
    jos sinulla on  avaintiedostoja paikallisella tietokoneella, niin
    voit tuoda sen suoraan. Jos avain on kelvollinen, niin se lisätään
    osoitekirjaasi   ja   ikkuna  sulkeutuu.   Jos   avain  ei   ollut
    kelvollinen, niin näkyviin  tulee virheilmoitus, jossa selvitetään
    mikä avaimessa oli vikana.
    </para>
</entry>

<entry id="pgp-overview-personalkey" md5="220af2b74a58f430efd72d6d6b1f993f" state="uptodate">
    <title>PGP: Henkilökohtaisten avainten hallinta</title>
    <heading>Yleiskuva</heading>
    <para>
    Jos haluat  sähköisesti allekirjoittaa tai  vastaanottaa salattuja
    sähköpostiviestejä, niin  sinulla pitää olla  oma henkilökohtainen
    julkinen/salainen PGP-avainpari.
    </para>
    <heading>Julkinen avaimesi</heading>
    <para>
    Julkinen   avaimesi   tulee   olla  saatavilla   kaikille   niille
    henkilöille,  joiden kanssa  haluat  kommunikoida salatusti  siten
    että vain  SINÄ voit avata sinulle tulleet  viestit. Lisäksi sinun
    tulee  laittaa  avain saataville  siten  että  ne, joille  lähetät
    sähköisesti    allekirjoitettuja    viestejä   voivat    tarkistaa
    allekirjoituksesi.
    </para>
    <heading>Salainen avaimesi</heading>
    <para>
    Salainen avain tarvitaan siihen että voisit purkaa sellaisen
    viestin, joka on salattu käyttäen julkista avainta. Lisäksi
    salaista avainta tarvitaan, jos haluat sähköisesti allekirjoittaa
    sähköpostiviestejä. Salainen avaimesi on suojattu niihin luonnin
    yhteydessä liitetyllä salasanatekstillä. Jos haluat käyttää
    sellaisia toimintoja, jotka käyttävät salaista avaintasi, niin
    silloin IMP kysyy sinulta tätä salasanateksti. Sinun ei tarvitse
    kirjoittaa salasanateksti kuin kerran yhden istunnon aikana - IMP
    muistaa annetun salasanatekstin siihen saakka kunnes kirjaudut
    ulos (Muista siis aina kirjautua ulos!).
    </para>
</entry>

<entry id="pgp-personalkey-public" md5="3c844d4ff8fdda3e0d446b47a63117e0" state="uptodate">
    <title>PGP: Henkilökohtaisten avainten hallinta - Julkinen avain</title>
    <heading>Näytä</heading>
    <para>
    Avaa uuden ikkunan jossa näkyy sinun julkinen PGP-avain.
    </para>
    <heading>Tarkemmat tiedot</heading>
    <para>
    Näyttää tarkempia tietoja julkisesta PGP-avaimestasi.
    </para>
</entry>

<entry id="pgp-personalkey-private" md5="1851b67a1aeef1242fc3a2b94af75c03" state="uptodate">
    <title>PGP: Henkilökohtaisten avainten hallinta - Salainen avain</title>
    <heading>Anna salasanateksti</heading>
    <para>
    Avaa erillisen ikkunan, jossa kysytään salasanatekstiä. Jos annat oikean salasanatekstin, niin IMP tallettaa tämän tiedon ja se on voimassa istunnon päättymiseen saakka.
    </para>
    <heading>Poista salasanateksti</heading>
    <para>
    Poistaa IMP-ohjelman muistista talletetun salasanateksti - tämän
    jälkeen jos salaista avainta tarvitaan johonkin toimintoon, niin
    se kysytään sinulta uudestaan.
    </para>
    <heading>Näytä</heading>
    <para>
    Avaa uuden ikkunan jossa näkyy salainen PGP-avaimesi. ÄLÄ KOSKAAN
    LÄHETÄ TÄTÄ AVAINTA KENELLEKKÄÄN - tämä toiminto on vain sitä
    varten että voit viedä ja käyttää avainta jossakin toisessa
    ohjelmassa.
    </para>
    <heading>Tarkemmat tiedot</heading>
    <para>
    Näyttää tarkempia tietoja salaisesta PGP-avaimestasi.
    </para>
</entry>

<entry id="pgp-personalkey-delete" md5="dbd8cbe6bce71c4fb592dd1b3b27b7ce" state="uptodate">
    <title>PGP: Henkilökohtaisten avainten hallinta - Poista</title>
    <heading>Poista henkilökohtaiset avaimet</heading>
    <para>
    Napauttamalla tätä painiketta voit poistaa julkinen/salainen
    PGP-avainparisi IMP-ohjelman asetuksista.
    </para>
</entry>

<entry id="pgp-personalkey-create-name" md5="748cb124b7ff52820792e278037a8c27" state="uptodate">
    <title>PGP: Luo henkilökohtainen avain - Nimi</title>
    <heading>Nimi</heading>
    <para>
    Nimi, jonka haluat sisällyttää henkilökohtaisiin
    avaimiisi. Pakollinen kenttä.
    </para>
</entry>

<entry id="pgp-personalkey-create-comment" md5="e666eb9f0ee4b49fe04f74fc18db8640" state="uptodate">
    <title>PGP: Luo henkilökohtainen avain - Kommentti</title>
    <heading>Kommentti</heading>
    <para>
    Kommentti, joka haluat sisällyttää henkilökohtaisiin
    avaimiisi. Vapaaehtoinen kenttä.
    </para>
</entry>

<entry id="pgp-personalkey-create-email" md5="c729f70fdb3a73cbb7ba5ef5888e3092" state="uptodate">
    <title>PGP: Luo henkilökohtainen avain - Sähköpostiosoite</title>
    <heading>Sähköpostiosoite</heading>
    <para>
    Sähköpostiosoite, jonka haluat liittää henkilökohtaisiin
    avaimiisi. Pakollinen kenttä.
    </para>
</entry>

<entry id="pgp-personalkey-create-keylength" md5="24ca641c63fb5ff310a39ee0d3b1ee55" state="uptodate">
    <title>PGP: Luo henkilökohtainen avain - Avaimen pituus</title>
    <heading>Avaimen pituus</heading>
    <para>
    Sinulle luotavan avaimen pituus tavuina. Mitä suurempi arvo, niin
    sen suurempi suoja, mutta myös suurempi luontiaika ja salaukseen
    käytetty aika). 1024 on oletusarvo - tämä on enemmän kuin riittävä
    avainpituus ja tarjoaa hyvän suojan.
    </para>
</entry>

<entry id="pgp-personalkey-create-passphrase" md5="2fb9372970bf33f51e988ba39dbd7193" state="uptodate">
    <title>PGP: Luo henkilökohtainen avain - Salasanateksti</title>
    <heading>Salasanateksti</heading>
    <para>
    Salasanateksti käytetään suojaamaan ja salaamaan henkilökohtaiset
    avaimesi. Tämä pitää olla VÄHINTÄÄN 6 merkkiä pitkä, EI SAA olla
    sama kuin mihinkään palveluun käyttämäsi salasana, ei tulisi olla
    sanakirjasta löytyvä sana ja tulisi sisältää sekä numeroita että
    kirjaimia. Varmuuden vuoksi sinun pitää kirjoittaa salasanateksti
    kahteen kertaan. Pakollinen kenttä.
    </para>
</entry>

<entry id="pgp-personalkey-create-actions" md5="0f8234935b964c83533b4ec4c15eb712" state="uptodate">
    <title>PGP: Luo henkilökohtainen avain - Toiminnot</title>
    <heading>Luo avaimet</heading>
    <para>
    Luo ja tallettaa henkilökohtaisen julkinen/salainen avainparin.
    </para>
    <heading>Tuo avainpari</heading>
    <para>
    Tästä painikkeesta aukeaa ikkuna, johon voi tuoda
    julkisen/salaisen avainparin. Voit kopioida ja liittää
    PGP-avainparin tekstikenttään tai jos sinulla on avaimet
    tiedostoina paikallisella tietokoneella, niin voit tuoda ne
    suoraan. Jos avaimet ovat kelvolliset, niin ne lisätään
    asetuksiisi ja ikkuna sulkeutuu. Jos avaimet eivät olleet
    kelvollisia, niin näkyviin tulee virheilmoitus, jossa selvitetään
    mikä avaimissa oli vikana.
    </para>
</entry>

<entry id="smime-overview" md5="d3c752b1345fb2eccfe575c07461963f" state="uptodate">
    <title>S/MIME: Yleiskuva</title>
    <heading>Mikä on S/MIME?</heading>
    <para>
    S/MIME on julkiseen ja salaiseen avaimeen perustuva avoin ja
    yhteensopiva järjestelmä, jonka avulla voi muodostaa sähköisiä
    allekirjoituksia, salata viesti ja suojata viestin eheys. S/MIME
    avulla voit salata viestit siten että vain viestin lähettäjä ja
    vastaanottaja voi sen lukea. Voit myös sähköisesti allekirjoittaa
    viestin, jolloin vastaanottaja voi tarkistaa että viesti on tullut
    juuri sinulta ja sitä ei ole muutettu matkalla. Yhdistämällä
    salaus ja sähköinen allekirjoitus voidaan taata viestin eheys ja
    se että kukaan muu kuin vastaanottaja ei pääse lukemaan viestiä.
    </para>
    <heading>Käytä S/MIME-toimintoa</heading>
    <para>
    Jos tämä asetus on valittuna, niin voit tuoda ohjelmaan
    henkilökohtaiset S/MIME-avaimet, lukea salattuja viestejä,
    tarkistaa sähköisiä allekirjoituksia ja voit kirjoittaa ja
    lähettää sähköisesti allekirjoitettuja salattuja viestejä.
    </para>
</entry>

<entry id="smime-overview-personalkey" md5="9f4f36ae72cb4abc731067d338be3b98" state="uptodate">
    <title>S/MIME: Henkilökohtaiset avaimet</title>
    <heading>Yleiskuva</heading>
    <para>
    Jos haluat lisätä viesteihin sähköisen allekirjoituksen tai salata
    viestejä, niin sinulla pitää olla julkinen/salainen
    S/MIME-avainpari.
    </para>
</entry>

<entry id="smime-import-personal-certs" md5="cf0ed2e3e24d30dedf8cfef2c2645759" state="uptodate">
    <title>S/MIME: Tuo henkilökohtaiset varmenteet</title>
    <heading>Tuo henkilökohtaiset varmenteet</heading>
    <para>
    Voit henkilökohtaiset varmenteesti, jos ne ovat PKCS #12
    muodossa. PKCS #12 muotoa käytetään yleisesti avainten viennissä
    esimerkiksi selaimista (esim. Internet Explorer, Firefox) tai jos
    avaimet halutaan viedä käyttöjärjestelmästä (esim. Windows
    XP). Jos avainmet ovat kelvolliset, niin ne lisätään asetuksiisi
    ja ikkuna sulkeutuu. Jos avaimet eivät olleet kelvollisia, niin
    näkyviin tulee virheilmoitus, jossa selvitetään mikä avaimissa oli
    vikana.
    </para>
</entry>

<entry id="smime-delete-personal-certs" md5="018bb6b61a7e416892de288ad1c880f4" state="uptodate">
    <title>S/MIME: Poista henkilökohtainen varmanne</title>
    <heading>Poista henkilökohtainen varmenne</heading>
    <para>
    Poistaa henkilökohtaisen varmenteen asetuksistasi. Tämän jälkeen et voi enää S/MIME-allekirjoittaa viestejä tai lukea sinulle osoitettuja S/MIME-salattuja viestejä.
    </para>
</entry>

<entry id="smime-manage-pubkey" md5="8b6c63684d3d73b3d084025a78fe7e88" state="uptodate">
    <title>S/MIME: Julkisten avaimien hallinta</title>
    <heading>S/MIME: Julkisten avaimien hallinta</heading>
    <para>
    Voit hallinnoida julkisten S/MIME-avainten listaa.
    </para>
    <heading>Näytä</heading>
    <para>
    Näyttää julkisen avaimen raakatekstiversiona.
    </para>
    <heading>Tarkemmat tiedot</heading>
    <para>
    Näyttää julkisen avaimen tarkemmat tekniset tiedot.
    </para>
    <heading>Poista</heading>
    <para>
    Poistaa valitun julkisen avaimen. Kun poistat jonkun käyttäjän
    julkisen avaimen, niin et voi enää lähettää hänelle salattuja
    viestejä.
    </para>
</entry>

<entry id="printing" md5="f233c11b6b4a6bedeb68f1d5a2a976db" state="uptodate">
    <title>Tulostus</title>
    <heading>Tulosta viesti</heading>
    <para>
    Tulostaaksesi katselemasi viestin, napsauta viestin alussa tai
    lopussa olevaa "Tulosta" -linkkiä. Viesti aukeaa uuteen ikkunaan
    tulostettavassa muodossa. Riippuen käytetystä selaimesta ja
    käyttöjärjestelmästä, niin sinulle pitäisi aueta
    tulostusdialogi. Jos dialogia ei tule, niin valitse selaimen
    "Tiedosto" -alasvetovalikosta toiminto "Tulosta".
    </para>
</entry>

<entry id="sorting" md5="18cdeac38027fe5c42bab693f2a4260a" state="uptodate">
    <title>Lajittelu ja säikeet</title>
    <heading>Lajittelu</heading>
    <para>
    Voit järjestää viestit eri sarakkeiden mukaan napauttamalla
    sarakkeen otsikkoa. Voit lajitella ne nousevaan tai laskevaan
    järjestykseen napauttamalla sarakkeen otsikon vieressä olevaa
    nuolenpään kuvaa.
    </para>
    <heading>Säikeet</heading>
    <para>
    Jos haluat järjestää viestit keskustelusäikeen mukaan, niin
    napsauta [Keskustelusäie] -linkkiä Otsikkosarakkeessa. Kun haluat
    palauttaa järjestyksen otsikon mukaiseksi, niin napsauta [Otsikko]
    linkkiä otsikkosarakkeessa.
    </para>
</entry>

<entry id="alternative-msg" md5="4978073f76977b6af6b69810e4d22a65" state="uptodate">
    <title>Multipart/Alternative viestit</title>
    <para>
    Lähettäjä on voinut lähettää jotkut viestit tyypillä
    "multipart/alternative". Näissä viesteissä on monta osiota, mutta
    niissä kaikissa on SAMA SISÄLTÖ, mutta ERI
    MUOTO. Sähköpostiohjelma pyrkii näyttämään näistä osioista sen,
    minkä se pystyy parhaiten näyttämään, viestin muut osiot näkyvät
    otsikon "Vaihtoehtoiset osat tälle osiolle:" alapuolella ja ne voi
    katsoa tai tallettaa erikseen. Kannattaa kuitenkin pitää mielessä
    että nämä vaihtoehtoiset osiot pitävät sisällään saman sisällön
    kuin se osio minkä sähköpostiohjelma näytti - osiot ovat vain eri
    muodossa (esimerkiksi teksti ja HTML-osiot).
    </para>
</entry>

<entry id="prefs-rename_sentmail_monthly" md5="530fa20e0afbc25ffd40877948832899" state="uptodate">
    <title>Asetukset: Ylläpitotoimenpiteet: Nimeä kuukausittain uudestaan lähetettyjen viestien kansiot</title>
    <para>
    Laita tämä asetus päälle, jos haluat kuukausittain nimetä
    uudelleen lähetettyjen viestien kansiot, niin kansiot nimetään
    uudestaan kuukauden alussa. Kansioiden uuteen nimeen lisätään
    kuukausi ja vuosi ja samalla luodaan myös uusi lähetettyjen
    viestien kansio.
    </para>
</entry>

<entry id="prefs-delete_sentmail_monthly" md5="0beed16dfd68e2f25e0c66871fd546df" state="uptodate">
    <title>Asetukset: Ylläpitotoimenpiteet: Poista kuukausittain lähetettyjen viestien kansio</title>
    <para>
    Laita tämä asetus päälle jos haluat joka kuukauden alussa poistaa
    vanhan lähetettyjen viestien kansion. Jos postilaatikollesi on
    asetettu kiintiö, niin tämä asetus voi olla hyödyllinen.
    </para>
</entry>

<entry id="prefs-delete_sentmail_monthly_keep" md5="71ed1c2eab48b91a25b5bcd4b14ccea9" state="uptodate">
    <title>Asetukset: Ylläpitotoimenpiteet: Poista kuukausittain lähetettyjen viestien kansio - # kansiota pidetään tallessa</title>
    <para>
    Jos poistat lähetettyjen viestien kansioita kuukausittain, niin
    kuinka monta vanhaa kansiota haluat pitää tallessa. Kaikki ne
    lähetettyjen viestien kansiot poistetaan, jotka ovat vanhempia
    kuin valittu määrä kuukausia.
    </para>
</entry>

<entry id="prefs-purge_sentmail" state="uptodate" md5="7b37c534aaaec6b43589f15845cf0273">
    <title>Asetukset: Ylläpitotoimet: tyhjennä lähettyjen viestien kansio</title>
    <para>
    Tällä asetuksella voi automaattisesti tyhjentää lähetettyjen viestien kansiota.
    </para>
</entry>

<entry id="prefs-purge_sentmail_interval" state="uptodate" md5="423f3c1b0645cee1bc58e6e22a6d8b68">
    <title>Asetukset: Ylläpitotoimet: lähettyjen viestien tyhjennysväli</title>
    <para>
    Jos lähetettyjen viestien kansiota tyhjennetään, niin tässä asetuksessa voit määritellä millaisin väliajoin kansiosta tyhjennetään vanhat viestit.
    </para>
</entry>

<entry id="prefs-purge_sentmail_keep" state="uptodate" md5="fcba2b7e5da61a7fdda7970f926f8d8a">
    <title>Asetukset: Ylläpitotoimet: Tyhjennä lähetetyjen viestien kansio</title>
    <para>
    Jos tyhjennät lähetettyjen viestien kansiot automaattisesti, niin kuinka vanhat viestit kansiosta pitäisi poistaa.
    </para>
</entry>

<entry id="prefs-delete_attachments_monthly" md5="373ea02ede6df5fc345caf632e19a75f" state="uptodate">
    <title>Asetukset: Ylläpitotoimenpiteet: Poista kuukausittain liitetyt liitetiedostot</title>
    <para>
    Laita tämä asetus päälle, jos haluat poistaa liitetiedostot joka
    kuukauden alussa. Jos postilaatikollesi on asetettu kiintiö, niin
    tämä asetus voi olla hyödyllinen.
    </para>
</entry>

<entry id="prefs-delete_attachments_monthly_keep" md5="1b340a60214dffd04aec02cc1127df5d" state="uptodate">
    <title>Asetukset: Ylläpitotoimenpiteet: Poista kuukausittain liitetyt liitetiedostot - # kuukauta vanhemmat</title>
    <para>
    Jos poistat liitetiedostoja kuukausittain, niin kuinka monta
    kuukautta vanhemmat liitetiedostot poistetaan? Jos jokin liite on
    tätä vanhempi, niin se poistetaan.
    </para>
</entry>

<entry id="prefs-purge_trash" md5="dc71871146be3e46ade0087a8cf18273" state="uptodate">
    <title>Asetukset: Ylläpitotoimenpiteet: Tyhjennä roskakori</title>
    <para>
    Kun haluat automaattisesti tyhjentää roskakorin tietyin väliajoin.
    </para>
</entry>

<entry id="prefs-purge_trash_interval" md5="7be91fbeb05b2d87289d4c5602d5a32f" state="uptodate">
    <title>Asetukset: Ylläpitotoimenpiteet: Tyhjennä roskakori väliajoin</title>
    <para>
    Jos tyhjennät roskakorikansiota automaattisesti, niin miten usein
    se pitäisi tyhjentää.
    </para>
</entry>

<entry id="prefs-purge_trash_keep" md5="3cb5a2b5b80b7ac1179ae005f983970e" state="uptodate">
    <title>&gt;Asetukset: Ylläpitotoimenpiteet: Tyhjennä roskakori viestien ikä</title>
    <para>
    Jos tyhjennät roskakorikansiota automaattisesti, niin montako
    päivää vanhemmat viestit tuhotaan automaattisesti.
    </para>
</entry>

<entry id="prefs-purge_spam" state="uptodate" md5="9cabaf3500d3316054db045cf5339f5e">
    <title>Asetukset: Ylläpitotoimenpiteet: Poista roskapostit</title>
    <para>
    Jos haluat poistaa roskapostit ajoittain.
    </para>
</entry>

<entry id="prefs-purge_spam_interval" state="uptodate" md5="fe0f7289693d19bd386638e25beeb276">
    <title>Asetukset: Ylläpitotoimenpiteet: Roskapostien poistamisen aikaväli</title>
    <para>
    Jos poistat roskapostiviestit automaattisesti, niin kuinka usen kansio pitäisi tyhjentää.
    </para>
</entry>

<entry id="prefs-purge_spam_keep" state="uptodate" md5="f4748aba20cf4a9b6ce92822bd185de6">
    <title>Asetukset ylläpitotoimenpiteet: Poistettavien roskapostiviestien ikä</title>
    <para>
    Jos tyhjennät roskapostikansiota automaattisesti, niin kuinka vanhat viestit kansiosta pitäisi poistaa.
    </para>
</entry>

<entry id="prefs-attrib_text" md5="721a09d7ca028c97e3bd2b38c597fff7" state="uptodate">
     <title>Asetukset: Viestin kirjoitus: Lainausteksti</title>
     <para>
     Tällä asetuksella voit määritellä mikä teksti laitetaan
     vastausviesteihin ennen lainattua tekstiä.
     </para>
     <para>
     Voit erikoiskoodien avulla laittaa laittaa määrittelytekstiin
     lisätietoja viestistä, johon olet vastaamassa. Erikoiskoodi
     koostuu '%'-merkistä ja sitä seuraa aina yksi kirjain tai
     merkki. Alla on lista, jossa on määritelty käytettävisä olevat
     erikoiskoodit.
     </para>

     <para> %f : Lähettäjän nimi ja sähköpostiosoite</para>
     <para> %a : Lähettäjän sähköpostiosoite</para>
     <para> %p : Lähettäjän nimi</para>
     <para> %r : RFC 2822 mukainen päivämäärä ja aikavyöhyke</para>
     <para> %d : Päivämäärä muodossa www, pp kkk VVVV</para>
     <para> %x : Päivämäärä esitettynä lokalisaation oletustavalla</para>
     <para> %c : Päivämäärä ja aika esitettynä lokalisaation oletustavalla</para>
     <para> %m : Message-ID</para>
     <para> %s : Otsikko</para>
     <para> %n : Rivinvaihto</para>
     <para> %% : '%' -merkki</para>

</entry>

<entry id="prefs-default_msg_charset" state="uptodate" md5="4ef4fb2090e703f6f8e03f39ab96e717">
    <title>Asetukset: Viestin oletusmerkistö</title>
    <para>
    Viestin oletusmerkistöä käytetään silloin kun viestin osioihin ei ole merkitty mitään merkistötietoa. RFC 2045 dokumentissä määritellään, että viestit joissa ei ole määritelty merkistötietoa näytetään käyttäen merkistöä 'US-ASCII'. Jotku rikkinäisen sähköpostiohjelmistot lähettävät viestejä siten, että tekstissä on käytetty US-ASCII ulkopuolisia merkkejä, mutta merkistötietoa ei ole määritelty. Tämän arvon voi asettaa siihen merkistöön, mitä yleisesti käytetään paikallisesti. Voit myös valita "Oletus", jolloin käytetään MIME-oletuksia.
    </para>
</entry>

<entry id="prefs-disposition_request_read" md5="89e92c4d68224b2345b59959878a7174" state="uptodate">
    <title>Asetukset: Pyydä ilmoitus viestin lukemisesta</title>
    <para>
    "Pyydä ilmoitus viestin lukemisesta" voi liittää viestiin pyynnön
    että sinulle lähtisi viesti kun vastaanottaja aukaisee
    viestin. Kaikki sähköpostiohjelmat eivät tue tätä toimintoa,
    lisäksi käyttäjä voi kieltää kuittausviestin lähettämisen.
    </para>
</entry>

<entry id="prefs-disposition_send_mdn" md5="1fe04e5dc3de68d172da284895973ea9" state="changed">
    <title>Asetukset: Lähetä MDN</title>
    <para>
    "Lähetä MDN" lähettää Message Disposition Notification (viestin
    aukaisun kuittausviesti) -ilmoitusviestin kun aukaiset viestin ja
    jos lähettäjä on pyytänyt että viestistä lähetetään
    kuittausviesti. Useimmissa tapauksissa tämä tapahtuu
    automaattisesti ilman että sinulta kysytään lupaa. Joidenkin
    viestien kohdalla voit joutua päättämään lähetetäänkö
    kuittausviestiä ja napsauttamaan linkkiä.
    </para>
<!-- English entry (2010-08-16):
<entry id="prefs-disposition_send_mdn">
    <title>Preferences: Send Read Receipt</title>
    <para>
    "Send a MDN" sends a read receipt (also known as a Message Disposition Notification) when you view a message in which the user has requested that they receive notification that you have read the message. By default, you will be prompted to send the notification. Other options include never sending these receipts or sending these receipts automatically without prompt if possible.
    </para>
</entry>--></entry>

<entry id="prefs-disposition_request_delivery" md5="26598e29af05a07de5e13644669be712" state="uptodate">
    <title>Asetukset: Pyydä ilmoitus viestin perillemenosta</title>
    <para>
    "Pyydä ilmoitus viestin perillemenosta" lähettää ilmoitusviestin
    kun vastaanottajan sähköpostipalvelin on toimittanut viestin
    vastaanottajan sähköpostikansioon. Tämä ei tarkoita sitä, että
    vastaanottaja olisi lukenut viestin vaan että viesti on toimitettu
    vastaanottajalle. Kaikki postipalvelimet eivät tue tätä toimintoa.
    </para>
</entry>

<entry id="prefs-delete_spam_after_report" state="changed" md5="cefa8b52e09b0ada90e0889a3959efea">
    <title>Asetukset: Poista roskaposti raportoinnin jälkeen</title>
    <para>Voit jonkun kolmesta asiasta kun olet raportoinut viestin joko roskapostina tai puhtaana.</para>
    <para>
    Yksi: Voit valita olla tekemättä mitään - viesti raportoidaan joko roskapostina tai puhtaana, mutta muuten se pysyy muuttumattomana postilaatikossasi.
    </para>
    <para>
    Kaksi: Jos viesti raportoidaan roskapostina, niin viesti poistetaan välittömästi postilaatikostasi. Jos viesti on puhdas, niin tämä vaihtoehto ei tee sille mitään.
    </para>
    <para>
    Kolme: Jos viesti raportoidaan roskapostina, niin viesti poistetaan nykyisestä postilaatikosta ja siirretään roskapostikansioosi. Jos raportoitava viesti on puhdas, niin viesti poistetaan nykyisestä postilaatikostasi ja siirretään INBOX postilaatikkoosi.
    </para>
<!-- English entry (2010-08-16):
<entry id="prefs-delete_spam_after_report">
    <title>Preferences: Delete Spam After Reporting</title>
    <para>
    You may elect to do one of three items after reporting a message as spam.
    </para>
    <para>
    First, you can decide to do nothing - the message will be reported as spam but will otherwise remain unchanged in your mailbox.
    </para>
    <para>
    Second, if reporting a message as spam, you can instead have the message be immediately deleted.
    </para>
    <para>
    Third, after reporting a message as spam the message will be deleted from the current mailbox and moved to your spam folder.
    </para>
</entry>--></entry>

<entry id="prefs-move_ham_after_report" state="new">
    <title>Preferences: Move Spam After Reporting As Innocent</title>
    <para>
    You may elect to do one of two items after reporting a message previously maked as spam as innocent.
    </para>
    <para>
    First, you can decide to do nothing - the message will be reported as innocent but will otherwise remain unchanged in your mailbox.
    </para>
    <para>
    Second, if reporting a message as innocent the message will be deleted from the current mailbox and moved to your Inbox.
    </para>
</entry>

<entry id="prefs-html_image_replacement" md5="28e1cf08e328345a8e7274c853492d4f" state="uptodate">
    <title>Asetukset: HTML, kuvan korvaus</title>
    <para>
    Jos HTML-viestit näytetään suoraan, niin estetääkö kuvien
    näyttäminen viestin yhteydessä ellet olet antanut siihen
    lupaa. Huomaathan että jos katsot HTML-liitettä, niin kuvat
    näytetään automaattisesti viestin mukana.
    </para>
</entry>

<entry id="prefs-html_image_addrbook" md5="759fa3df24e0a3cd89f320102252f91a" state="uptodate">
    <title>Asetukset: HTML, kuvan korvaus / Näytä jos osoitekirjassa</title>
    <para>
    Jos HTML-viesteistä ei oletuksena näytetä kuvia viestin
    yhteydessä, niin näytetäänkö kuvat jos lähettäjän sähköpostiosoite
    löytyy osoitekirjasta.
    </para>
</entry>

<entry id="prefs-mailbox_start" md5="62fcc38a15f54dae7eb8bdafa93ed341" state="uptodate">
    <title>Asetukset: Postilaatikon aloitussivu</title>
    <para>
    Tällä asetuksella voidaan määritellä mille sivulle postikansio
    aukeaa, kun se avataan ensimmäistä kertaa. Huomaa että "uusi"
    viestiasetus ei toimi, jos sinulla on valittuna "Keskustelusäie"
    järjestysasetus - tässä tapauksessa aukeaa aina viimeisin
    viestisivu.
    </para>
</entry>

<entry id="prefs-save_attachments" md5="35b46334cdcc7fa416b9f9fca5874e80" state="uptodate">
    <title>Asetukset: Talleta liitetiedostot lähetetyistä viesteistä</title>
    <para>
    Jos talletat lähetetyt viesti lähetettyjen viestien kansioon, niin talletetaanko viestien mukana myös liitetiedosto. Vaihtoehtoja ovat:
    </para>

    <para>* "Talleta aina liitteet" - ÄLÄ KOSKAAN kysy talletetaanko liitteitä. Liitteet talletaan AINA viestin mukana.</para>
     <para>* "Kysy aina kun lähetetään liitetiedosto; Oletus KYLLÄ" - Kysy AINA talletaanko liitteet viestin mukana. Oletus on että liitteet talletaan viestin mukana.</para>
     <para>* "Kysy aina kun lähetetään liitetiedosto; Oletus EI" - Kysy AINA talletaanko liitteet viestin mukana. Oletus on että liitteitä ei talleteta viestin mukana.</para>
     <para>* "Älä talleta liitteitä" ÄLÄ KOSKAAN kysy talletetaanko liitteitä. Liitteitä EI IKINÄ talleteta viestin mukana.</para>
</entry>

<entry id="virtual_inbox" state="uptodate" md5="a91e01732bb8129cbc6a7f5c6dca3ab3">
    <title>Virtuaaliset kansiot: Virtuaalinen Inbox</title>
    <para>
    Virtuaalinen Inbox on talletettu haku, joka tekee tarpeettomaksi etsiä uusiksi merkittyjä viestejä kaikista postilaatikoista. Tämän sijaan uusia viestejä etsitään vain tilatuista postilaatikoista ja haun tulos näytetään yhtenä virtuaalisena kansiona.
    </para>
</entry>

<entry id="virtual_trash" state="uptodate" md5="b83f73ed56dff0addcbd4702e5a21a3d">
    <title>Virtuaaliset kansiot: Virtuaalinen roskakori</title>
    <para>
    Virtuaalinen roskakori on talletettu haku, joka voi korvata tarpeen erillisille roskakorikansiolle. Sen sijaan, että viestit siirretään erilliseen roskakorikansioon, niin ne merkitään poistettavaksi ja viesti pysyy nykyisessä kansiossa. Kun vielä on päällä asetus 'Piilota poistetut', niin viestit eivät näy viestilistauksessa. Kun käyttäjä napsauttaa Virtuaalinen roskakori, niin poistetuksi merkittyjä kansioita etsitään kaikista kansioista ja nämä viestit näytetään yyhtenä virtuaalisena kansiona.
    </para>
</entry>

</help>
